<annotation>
	<folder>house sparrow</folder>
	<filename>290.jpeg</filename>
	<path>/home/reetvik/Desktop/house sparrow/290.jpeg</path>
	<source>
		<database>Unknown</database>
	</source>
	<size>
		<width>201</width>
		<height>251</height>
		<depth>3</depth>
	</size>
	<segmented>0</segmented>
	<object>
		<name>hsparrow</name>
		<pose>Unspecified</pose>
		<truncated>0</truncated>
		<difficult>0</difficult>
		<bndbox>
			<xmin>31</xmin>
			<ymin>27</ymin>
			<xmax>171</xmax>
			<ymax>97</ymax>
		</bndbox>
	</object>
	<object>
		<name>hsparrow</name>
		<pose>Unspecified</pose>
		<truncated>0</truncated>
		<difficult>0</difficult>
		<bndbox>
			<xmin>110</xmin>
			<ymin>139</ymin>
			<xmax>160</xmax>
			<ymax>200</ymax>
		</bndbox>
	</object>
</annotation>
