<annotation>
	<folder>house sparrow</folder>
	<filename>546.jpeg</filename>
	<path>/home/reetvik/Desktop/house sparrow/546.jpeg</path>
	<source>
		<database>Unknown</database>
	</source>
	<size>
		<width>194</width>
		<height>259</height>
		<depth>3</depth>
	</size>
	<segmented>0</segmented>
	<object>
		<name>hsparrow</name>
		<pose>Unspecified</pose>
		<truncated>0</truncated>
		<difficult>0</difficult>
		<bndbox>
			<xmin>58</xmin>
			<ymin>38</ymin>
			<xmax>160</xmax>
			<ymax>220</ymax>
		</bndbox>
	</object>
</annotation>
