<annotation>
	<folder>my-project-name</folder>
	<filename>686.jpeg</filename>
	<path>/my-project-name/686.jpeg</path>
	<source>
		<database>Unspecified</database>
	</source>
	<size>
		<width>289</width>
		<height>175</height>
		<depth>3</depth>
	</size>
	<object>
		<name>home_sparrow</name>
		<pose>Unspecified</pose>
		<truncated>Unspecified</truncated>
		<difficult>Unspecified</difficult>
		<bndbox>
			<xmin>116</xmin>
			<ymin>63</ymin>
			<xmax>177</xmax>
			<ymax>120</ymax>
		</bndbox>
	</object>
</annotation>